hbbrain/__init__.py
hbbrain/_check_version.py
hbbrain/_min_dependencies.py
hbbrain/_structures.py
hbbrain/constants.py
hbbrain/datasets.py
hbbrain/setup.py
hbbrain/base/__init__.py
hbbrain/base/base_ensemble.py
hbbrain/base/base_estimator.py
hbbrain/base/base_fmnn_estimator.py
hbbrain/base/base_gfmm_estimator.py
hbbrain/mixed_data/__init__.py
hbbrain/mixed_data/eiol_gfmm.py
hbbrain/mixed_data/freq_cat_onln_gfmm.py
hbbrain/mixed_data/onehot_onln_gfmm.py
hbbrain/numerical_data/__init__.py
hbbrain/numerical_data/setup.py
hbbrain/numerical_data/batch_learner/__init__.py
hbbrain/numerical_data/batch_learner/accel_agglo_gfmm.py
hbbrain/numerical_data/batch_learner/agglo_gfmm.py
hbbrain/numerical_data/ensemble_learner/__init__.py
hbbrain/numerical_data/ensemble_learner/base_bagging.py
hbbrain/numerical_data/ensemble_learner/base_cross_val_bagging.py
hbbrain/numerical_data/ensemble_learner/cross_val_random_hyperboxes.py
hbbrain/numerical_data/ensemble_learner/decision_comb_bagging.py
hbbrain/numerical_data/ensemble_learner/decision_comb_cross_val_bagging.py
hbbrain/numerical_data/ensemble_learner/model_comb_bagging.py
hbbrain/numerical_data/ensemble_learner/model_comb_cross_val_bagging.py
hbbrain/numerical_data/ensemble_learner/random_hyperboxes.py
hbbrain/numerical_data/incremental_learner/__init__.py
hbbrain/numerical_data/incremental_learner/efmnn.py
hbbrain/numerical_data/incremental_learner/fmnn.py
hbbrain/numerical_data/incremental_learner/inf_onln_gfmm.py
hbbrain/numerical_data/incremental_learner/iol_gfmm.py
hbbrain/numerical_data/incremental_learner/knefmnn.py
hbbrain/numerical_data/incremental_learner/onln_gfmm.py
hbbrain/numerical_data/incremental_learner/rfmnn.py
hbbrain/numerical_data/multigranular_learner/__init__.py
hbbrain/numerical_data/multigranular_learner/base_granular_learner.py
hbbrain/numerical_data/multigranular_learner/multi_resolution_gfmm.py
hbbrain/tests/__init__.py
hbbrain/tests/test_adjust_hyperbox.py
hbbrain/tests/test_dist_metrics.py
hyperbox_brain-0.1.6.dist-info/LICENSE
hyperbox_brain-0.1.6.dist-info/METADATA
hyperbox_brain-0.1.6.dist-info/WHEEL
hyperbox_brain-0.1.6.dist-info/top_level.txt
hyperbox_brain-0.1.6.dist-info/RECORD
