Metadata-Version: 2.1
Name: hyperbox-brain
Version: 0.1.6
Summary: A scikit-learn compatible hyperbox-based machine learning library in Python
Home-page: https://uts-caslab.github.io/hyperbox-brain/
Download-URL: https://pypi.org/project/hyperbox-brain/#files
Maintainer: Thanh Tung KHUAT
Maintainer-email: thanhtung09t2@gmail.com
License: GPLv3
Project-URL: Bug Tracker, https://github.com/UTS-CASLab/hyperbox-brain/issues
Project-URL: Documentation, https://hyperbox-brain.readthedocs.io/en/stable/
Project-URL: Source Code, https://github.com/UTS-CASLab/hyperbox-brain
Classifier: Intended Audience :: Science/Research
Classifier: Intended Audience :: Developers
Classifier: License :: OSI Approved :: GNU General Public License v3 (GPLv3)
Classifier: Programming Language :: Python
Classifier: Topic :: Software Development
Classifier: Topic :: Scientific/Engineering
Classifier: Development Status :: 5 - Production/Stable
Classifier: Operating System :: Microsoft :: Windows
Classifier: Operating System :: POSIX
Classifier: Operating System :: Unix
Classifier: Operating System :: MacOS
Classifier: Programming Language :: Python :: 3.6
Classifier: Programming Language :: Python :: 3.7
Classifier: Programming Language :: Python :: 3.8
Classifier: Programming Language :: Python :: 3.9
Classifier: Programming Language :: Python :: 3.10
Classifier: Programming Language :: Python :: Implementation :: PyPy
Requires-Python: >=3.6
License-File: LICENSE
Requires-Dist: numpy (>=1.14.6)
Requires-Dist: scipy (>=1.1.0)
Requires-Dist: joblib (>=0.11)
Requires-Dist: threadpoolctl (>=2.0.0)
Requires-Dist: scikit-learn (>=0.24.0)
Requires-Dist: matplotlib (>=2.2.3)
Requires-Dist: pandas (>=0.25.0)
Requires-Dist: plotly (>=4.10.0)
Provides-Extra: docs
Requires-Dist: numpy (>=1.14.6) ; extra == 'docs'
Requires-Dist: scipy (>=1.1.0) ; extra == 'docs'
Requires-Dist: joblib (>=0.11) ; extra == 'docs'
Requires-Dist: threadpoolctl (>=2.0.0) ; extra == 'docs'
Requires-Dist: scikit-learn (>=0.24.0) ; extra == 'docs'
Requires-Dist: matplotlib (>=2.2.3) ; extra == 'docs'
Requires-Dist: pandas (>=0.25.0) ; extra == 'docs'
Requires-Dist: plotly (>=4.10.0) ; extra == 'docs'
Requires-Dist: sphinx (>=4.0.1) ; extra == 'docs'
Requires-Dist: sphinx-gallery (>=0.7.0) ; extra == 'docs'
Requires-Dist: numpydoc (>=1.0.0) ; extra == 'docs'
Requires-Dist: Pillow (>=7.1.2) ; extra == 'docs'
Requires-Dist: sphinx-prompt (>=1.3.0) ; extra == 'docs'
Requires-Dist: sphinxext-opengraph (>=0.4.2) ; extra == 'docs'
Requires-Dist: sphinx-autodocgen (>=1.3) ; extra == 'docs'
Provides-Extra: examples
Requires-Dist: scikit-learn (>=0.24.0) ; extra == 'examples'
Requires-Dist: matplotlib (>=2.2.3) ; extra == 'examples'
Requires-Dist: pandas (>=0.25.0) ; extra == 'examples'
Requires-Dist: plotly (>=4.10.0) ; extra == 'examples'
Provides-Extra: tests
Requires-Dist: scikit-learn (>=0.24.0) ; extra == 'tests'
Requires-Dist: matplotlib (>=2.2.3) ; extra == 'tests'
Requires-Dist: pandas (>=0.25.0) ; extra == 'tests'
Requires-Dist: pytest (>=5.0.1) ; extra == 'tests'
Requires-Dist: pytest-cov (>=2.9.0) ; extra == 'tests'
Requires-Dist: flake8 (>=3.8.2) ; extra == 'tests'
Requires-Dist: black (>=22.3.0) ; extra == 'tests'
Requires-Dist: mypy (>=0.770) ; extra == 'tests'
Requires-Dist: pyamg (>=4.0.0) ; extra == 'tests'
